{
  "generatedAt": "2026-04-24T00:12:29.549Z",
  "matchups": {
    "cavaliers vs. raptors": "B0GXBXNDPS",
    "celtics vs. 76ers": "B0GR94L7RL",
    "defensa y justicia vs. boca juniors": "0JV9P0QW0XCY5SNETXEK98XIT6",
    "gaskins vs. guymon: weigh-in": "0U87T4TJ6K96VERXK26KYA5X15",
    "knicks vs. hawks": "B0GX7BG6CY",
    "lakers vs. rockets": "0POORW330B53T12CWY9B4EFK7D",
    "nuggets vs. timberwolves": "0P72Q0IIB7KYHKOV15GXAYK4QJ",
    "spurs vs. trail blazers": "0OP2D36TZU1RJXL48A9HECCXK0"
  }
}
