{"fetchedAt":"2026-04-24T00:24:50.344Z","items":[{"id":"https://www.cbssports.com/nfl/draft/news/renner-2026-nfl-mock-draft-final/","headline":"Renner's final 2026 NFL mock draft: Cowboys storm into top 10, Giants load up with third first-rounder","description":"","published":"2026-04-24T00:22:48.000Z","imageUrl":null,"articleUrl":"https://www.cbssports.com/nfl/draft/news/renner-2026-nfl-mock-draft-final/","byline":"","section":"CBS Sports"},{"id":"https://www.cbssports.com/nfl/draft/news/nfl-draft-picks-by-team-2026-full-list/","headline":"2026 NFL Draft picks by team: Full list of all 257 picks, plus every selection for all 32 teams","description":"","published":"2026-04-24T00:20:53.000Z","imageUrl":null,"articleUrl":"https://www.cbssports.com/nfl/draft/news/nfl-draft-picks-by-team-2026-full-list/","byline":"","section":"CBS Sports"},{"id":"https://www.cbssports.com/nfl/draft/news/nfl-draft-2026-team-grades/","headline":"2026 NFL Draft team grades: Live updates for all 32 teams as Round 1 unfolds","description":"","published":"2026-04-24T00:19:53.000Z","imageUrl":null,"articleUrl":"https://www.cbssports.com/nfl/draft/news/nfl-draft-2026-team-grades/","byline":"","section":"CBS Sports"},{"id":"https://www.cbssports.com/nfl/draft/news/2026-nfl-draft-grades-tracker-live-round-1-analysis/","headline":"2026 NFL Draft grades, tracker: Live Round 1 analysis for every selection made in order","description":"","published":"2026-04-24T00:20:44.000Z","imageUrl":null,"articleUrl":"https://www.cbssports.com/nfl/draft/news/2026-nfl-draft-grades-tracker-live-round-1-analysis/","byline":"","section":"CBS Sports"},{"id":"https://www.cbssports.com/nfl/news/mike-vrabel-counseling-off-field-patriots-nfl-draft/","headline":"Patriots' Mike Vrabel addresses stepping away for Day 3 of NFL Draft amid off-field matter","description":"","published":"2026-04-24T00:05:51.000Z","imageUrl":null,"articleUrl":"https://www.cbssports.com/nfl/news/mike-vrabel-counseling-off-field-patriots-nfl-draft/","byline":"","section":"CBS Sports"},{"id":"https://www.cbssports.com/nfl/draft/news/raiders-draft-fernando-mendoza-no-1-nfl-draft-2026/","headline":"Raiders draft Fernando Mendoza No. 1: The pick that must end decades of draft failure","description":"","published":"2026-04-24T00:12:15.000Z","imageUrl":null,"articleUrl":"https://www.cbssports.com/nfl/draft/news/raiders-draft-fernando-mendoza-no-1-nfl-draft-2026/","byline":"","section":"CBS Sports"},{"id":"https://www.cbssports.com/nfl/draft/news/nfl-draft-2026-how-to-watch/","headline":"2026 NFL Draft is underway: How to watch, full order and top prospects for Round 1","description":"","published":"2026-04-24T00:00:52.000Z","imageUrl":null,"articleUrl":"https://www.cbssports.com/nfl/draft/news/nfl-draft-2026-how-to-watch/","byline":"","section":"CBS Sports"},{"id":"https://www.cbssports.com/nfl/news/george-pickens-landing-spots-2026-nfl-draft/","headline":"George Pickens landing spots: Where Pro Bowl WR could be traded during 2026 NFL Draft","description":"","published":"2026-04-23T23:43:15.000Z","imageUrl":null,"articleUrl":"https://www.cbssports.com/nfl/news/george-pickens-landing-spots-2026-nfl-draft/","byline":"","section":"CBS Sports"},{"id":"https://www.cbssports.com/nfl/news/2026-nfl-draft-ty-simpsons-rams/","headline":"2026 NFL Draft: Ty Simpson's tie to the Rams goes through his father and Les Snead","description":"","published":"2026-04-23T22:50:53.000Z","imageUrl":null,"articleUrl":"https://www.cbssports.com/nfl/news/2026-nfl-draft-ty-simpsons-rams/","byline":"","section":"CBS Sports"},{"id":"https://www.cbssports.com/nfl/news/cowboys-draft-picks-2026-tracker-grades-analysis/","headline":"Dallas Cowboys NFL Draft tracker: Picks, grades, analysis for every selection","description":"","published":"2026-04-23T22:28:36.000Z","imageUrl":null,"articleUrl":"https://www.cbssports.com/nfl/news/cowboys-draft-picks-2026-tracker-grades-analysis/","byline":"","section":"CBS Sports"},{"id":"https://www.cbssports.com/nfl/news/cowboys-halt-long-term-contract-talks-george-pickens-franchise-tag/","headline":"George Pickens signing franchise tag after Cowboys halt long-term contract talks","description":"","published":"2026-04-23T22:17:40.000Z","imageUrl":null,"articleUrl":"https://www.cbssports.com/nfl/news/cowboys-halt-long-term-contract-talks-george-pickens-franchise-tag/","byline":"","section":"CBS Sports"},{"id":"https://www.cbssports.com/betting/news/2026-nfl-draft-odds-tracker-top-10-picks/","headline":"2026 NFL Draft odds tracker: See how top 10 picks change following Giants-Bengals trade as Draft Day nears","description":"","published":"2026-04-23T21:05:59.000Z","imageUrl":null,"articleUrl":"https://www.cbssports.com/betting/news/2026-nfl-draft-odds-tracker-top-10-picks/","byline":"","section":"CBS Sports"}]}