{"fetchedAt":"2026-05-11T03:03:14.102Z","items":[{"id":"48738058","headline":"Detroit Tigers vs. Kansas City Royals: Game Highlights","description":"","published":"2026-05-11T03:00:07Z","imageUrl":null,"leagueLogo":"https://a.espncdn.com/i/espn/misc_logos/500/espn.png","articleUrl":"https://www.espn.com/video/clip/_/id/48738058/game-highlights","byline":"","section":"ESPN"},{"id":"48737913","headline":"Anthony Edwards rallies Timberwolves to even series with Spurs","description":"","published":"2026-05-11T02:53:26Z","imageUrl":null,"leagueLogo":"https://a.espncdn.com/combiner/i?img=/i/teamlogos/leagues/500/nba.png&w=40&h=40&transparent=true","articleUrl":"https://www.espn.com/nba/story/_/id/48737913/anthony-edwards-rallies-timberwolves-even-series-spurs","byline":"","section":"ESPN"},{"id":"48737677","headline":"Canadiens beat Sabres 6-2 to take a 2-1 lead in the second-round Eastern Conference series","description":"","published":"2026-05-11T02:29:13Z","imageUrl":null,"leagueLogo":"https://a.espncdn.com/combiner/i?img=/i/teamlogos/leagues/500/nhl.png&w=40&h=40&transparent=true","articleUrl":"http://www.espn.com/nhl/recap?gameId=401871406","byline":"","section":"ESPN"},{"id":"48722651","headline":"QB Anthony Richardson giving Colts something to think about","description":"","published":"2026-05-10T11:36:06Z","imageUrl":null,"leagueLogo":"https://a.espncdn.com/combiner/i?img=/i/teamlogos/leagues/500/nfl.png&w=40&h=40&transparent=true","articleUrl":"https://www.espn.com/nfl/story/_/id/48722651/qb-anthony-richardson-giving-colts-think-about","byline":"","section":"ESPN"},{"id":"48736029","headline":"Burley blasts 'hypocrite' Arteta in huge refereeing rant","description":"","published":"2026-05-10T23:04:46Z","imageUrl":null,"leagueLogo":"https://a.espncdn.com/i/espn/misc_logos/500/espn.png","articleUrl":"https://www.espn.com/video/clip/_/id/48736029/burley-blasts-hypocrite-arteta-huge-refereeing-rant","byline":"","section":"ESPN"},{"id":"48737952","headline":"Workman lives up to middle name with 1st career homer as Tigers top Royals 6-3 to stop skid","description":"","published":"2026-05-11T02:50:02Z","imageUrl":null,"leagueLogo":"https://a.espncdn.com/combiner/i?img=/i/teamlogos/leagues/500/mlb.png&w=40&h=40&transparent=true","articleUrl":"http://www.espn.com/mlb/recap?gameId=401815291","byline":"","section":"ESPN"},{"id":"48737861","headline":"San Antonio Spurs vs. Minnesota Timberwolves: Game Highlights","description":"","published":"2026-05-11T02:38:32Z","imageUrl":null,"leagueLogo":"https://a.espncdn.com/i/espn/misc_logos/500/espn.png","articleUrl":"https://www.espn.com/video/clip/_/id/48737861/game-highlights","byline":"","section":"ESPN"},{"id":"48737663","headline":"Buffalo Sabres vs. Montreal Canadiens: Game Highlights","description":"","published":"2026-05-11T02:25:39Z","imageUrl":null,"leagueLogo":"https://a.espncdn.com/i/espn/misc_logos/500/espn.png","articleUrl":"https://www.espn.com/video/clip/_/id/48737663/game-highlights","byline":"","section":"ESPN"},{"id":"48714977","headline":"Bengals' second-rounder Cashius Howell eyes sack celebration","description":"","published":"2026-05-10T10:00:01Z","imageUrl":null,"leagueLogo":"https://a.espncdn.com/combiner/i?img=/i/teamlogos/leagues/500/nfl.png&w=40&h=40&transparent=true","articleUrl":"https://www.espn.com/nfl/story/_/id/48714977/cincinnati-bengals-second-rounder-cashius-howell-eyes-sack-celebration","byline":"","section":"ESPN"},{"id":"48735127","headline":"Nuno: 'Everyone is confused by VAR consistency'","description":"","published":"2026-05-10T22:23:33Z","imageUrl":null,"leagueLogo":"https://a.espncdn.com/i/espn/misc_logos/500/espn.png","articleUrl":"https://www.espn.com/video/clip/_/id/48735127/everyone-confused-var-consistency","byline":"","section":"ESPN"},{"id":"48736581","headline":"St. Louis Cardinals vs. San Diego Padres: Game Highlights","description":"","published":"2026-05-11T00:15:06Z","imageUrl":null,"leagueLogo":"https://a.espncdn.com/i/espn/misc_logos/500/espn.png","articleUrl":"https://www.espn.com/video/clip/_/id/48736581/game-highlights","byline":"","section":"ESPN"},{"id":"48737809","headline":"Edwards guides the Timberwolves past the Spurs 114-109 to tie the series after Wembanyama's ejection","description":"","published":"2026-05-11T02:32:02Z","imageUrl":null,"leagueLogo":"https://a.espncdn.com/combiner/i?img=/i/teamlogos/leagues/500/nba.png&w=40&h=40&transparent=true","articleUrl":"http://www.espn.com/nba/recap?gameId=401871155","byline":"","section":"ESPN"},{"id":"48485622","headline":"Stanley Cup playoffs 2026: Bracket, schedule, scores, news","description":"","published":"2026-05-11T02:03:42Z","imageUrl":null,"leagueLogo":"https://a.espncdn.com/combiner/i?img=/i/teamlogos/leagues/500/nhl.png&w=40&h=40&transparent=true","articleUrl":"https://www.espn.com/nhl/story/_/id/48485622/nhl-playoffs-2026-stanley-cup-bracket-schedule-teams-players-preview","byline":"","section":"ESPN"},{"id":"48713940","headline":"Does Patriots' rookie TE Eli Raridon have untapped potential?","description":"","published":"2026-05-10T13:43:21Z","imageUrl":null,"leagueLogo":"https://a.espncdn.com/combiner/i?img=/i/teamlogos/leagues/500/nfl.png&w=40&h=40&transparent=true","articleUrl":"https://www.espn.com/nfl/story/_/id/48713940/does-new-england-patriots-rookie-te-eli-raridon-untapped-potential","byline":"","section":"ESPN"},{"id":"48734169","headline":"Manchester City's Doku has mindset to rival world's best, Pep says","description":"","published":"2026-05-10T21:30:35Z","imageUrl":null,"leagueLogo":"https://a.espncdn.com/redesign/assets/img/icons/ESPN-icon-soccer.png","articleUrl":"https://www.espn.com/soccer/story/_/id/48734169/manchester-city-doku-mindset-rival-world-best","byline":"","section":"ESPN"}]}