{"fetchedAt":"2026-05-10T05:10:45.653Z","items":[{"id":"48728213","headline":"Pirates get a season-high 20 hits and beat the Giants 13-3","description":"","published":"2026-05-10T04:43:01Z","imageUrl":null,"leagueLogo":"https://a.espncdn.com/combiner/i?img=/i/teamlogos/leagues/500/mlb.png&w=40&h=40&transparent=true","articleUrl":"http://www.espn.com/mlb/recap?gameId=401815281","byline":"","section":"ESPN"},{"id":"48727898","headline":"Charles Barkley thanks the inventor of tartar sauce","description":"","published":"2026-05-10T04:13:51Z","imageUrl":null,"leagueLogo":"https://a.espncdn.com/i/espn/misc_logos/500/espn.png","articleUrl":"https://www.espn.com/video/clip/_/id/48727898/charles-barkley-thanks-inventor-tartar-sauce","byline":"","section":"ESPN"},{"id":"48728025","headline":"Jesper Wallstedt makes most of 2nd chance, leads Wild to win","description":"","published":"2026-05-10T04:39:48Z","imageUrl":null,"leagueLogo":"https://a.espncdn.com/combiner/i?img=/i/teamlogos/leagues/500/nhl.png&w=40&h=40&transparent=true","articleUrl":"https://www.espn.com/nhl/story/_/id/48728025/jesper-wallstedt-makes-most-2nd-chance-leads-wild-win","byline":"","section":"ESPN"},{"id":"48724681","headline":"Ex-Jet Wint to fight for UFC deal on Dana White's Contender Series","description":"","published":"2026-05-09T22:37:55Z","imageUrl":null,"leagueLogo":"https://a.espncdn.com/combiner/i?img=/i/teamlogos/leagues/500/ufc.png&w=40&h=40&transparent=true","articleUrl":"https://www.espn.com/mma/story/_/id/48724681/ex-nfl-player-wint-fight-dana-white-contender-series","byline":"","section":"ESPN"},{"id":"48725772","headline":"Liverpool and Chelsea play out 1-1 stalemate","description":"","published":"2026-05-09T23:58:50Z","imageUrl":null,"leagueLogo":"https://a.espncdn.com/i/espn/misc_logos/500/espn.png","articleUrl":"https://www.espn.com/video/clip/_/id/48725772/liverpool-chelsea-play-1-1-stalemate","byline":"","section":"ESPN"},{"id":"48305211","headline":"2026 MLB ABS challenge system tracker: Team, player rankings","description":"","published":"2026-05-10T04:49:06Z","imageUrl":null,"leagueLogo":"https://a.espncdn.com/combiner/i?img=/i/teamlogos/leagues/500/mlb.png&w=40&h=40&transparent=true","articleUrl":"https://www.espn.com/mlb/story/_/id/48305211/2026-mlb-abs-challenge-system-tracker-team-player-rankings","byline":"","section":"ESPN"},{"id":"48419498","headline":"2026 NBA playoffs: Schedule, scores, news and highlights","description":"","published":"2026-05-10T03:35:46Z","imageUrl":null,"leagueLogo":"https://a.espncdn.com/combiner/i?img=/i/teamlogos/leagues/500/nba.png&w=40&h=40&transparent=true","articleUrl":"https://www.espn.com/nba/story/_/id/48419498/nba-playoffs-2026-play-finals-schedule-scores-news-highlights-bracket-dates","byline":"","section":"ESPN"},{"id":"48727955","headline":"Colorado Avalanche vs. Minnesota Wild: Game Highlights","description":"","published":"2026-05-10T03:55:39Z","imageUrl":null,"leagueLogo":"https://a.espncdn.com/i/espn/misc_logos/500/espn.png","articleUrl":"https://www.espn.com/video/clip/_/id/48727955/game-highlights","byline":"","section":"ESPN"},{"id":"48724463","headline":"Jets QB Klubnik unshaken by fall in draft: 'I'm a winner'","description":"","published":"2026-05-09T22:50:17Z","imageUrl":null,"leagueLogo":"https://a.espncdn.com/combiner/i?img=/i/teamlogos/leagues/500/nfl.png&w=40&h=40&transparent=true","articleUrl":"https://www.espn.com/nfl/story/_/id/48724463/jets-qb-klubnik-unshaken-fall-draft-winner","byline":"","section":"ESPN"},{"id":"48725515","headline":"Manchester City crush Brentford to keep title hopes alive","description":"","published":"2026-05-09T23:12:31Z","imageUrl":null,"leagueLogo":"https://a.espncdn.com/i/espn/misc_logos/500/espn.png","articleUrl":"https://www.espn.com/video/clip/_/id/48725515/manchester-city-crush-brentford-keep-title-hopes-alive","byline":"","section":"ESPN"},{"id":"48728170","headline":"Pittsburgh Pirates vs. San Francisco Giants: Game Highlights","description":"","published":"2026-05-10T04:35:21Z","imageUrl":null,"leagueLogo":"https://a.espncdn.com/i/espn/misc_logos/500/espn.png","articleUrl":"https://www.espn.com/video/clip/_/id/48728170/game-highlights","byline":"","section":"ESPN"},{"id":"48727515","headline":"Thunder blow by Lakers in Game 3, improve to 7-0 in playoffs","description":"","published":"2026-05-10T03:58:27Z","imageUrl":null,"leagueLogo":"https://a.espncdn.com/combiner/i?img=/i/teamlogos/leagues/500/nba.png&w=40&h=40&transparent=true","articleUrl":"https://www.espn.com/nba/story/_/id/48727515/thunder-blow-lakers-game-3-improve-7-0-playoffs","byline":"","section":"ESPN"},{"id":"48727950","headline":"Kaprizov gets the Wild going with a goal and two assists in a 5-1 win to hand the Avs their 1st loss","description":"","published":"2026-05-10T05:08:10Z","imageUrl":null,"leagueLogo":"https://a.espncdn.com/combiner/i?img=/i/teamlogos/leagues/500/nhl.png&w=40&h=40&transparent=true","articleUrl":"http://www.espn.com/nhl/recap?gameId=401871418","byline":"","section":"ESPN"},{"id":"48724018","headline":"Broncos' Sean Payton: Bo Nix on track for limited minicamp participation","description":"","published":"2026-05-09T21:49:34Z","imageUrl":null,"leagueLogo":"https://a.espncdn.com/combiner/i?img=/i/teamlogos/leagues/500/nfl.png&w=40&h=40&transparent=true","articleUrl":"https://www.espn.com/nfl/story/_/id/48724018/bo-nix-track-limited-minicamp-participation","byline":"","section":"ESPN"},{"id":"48724796","headline":"'Come on you Irons!' - Guardiola sends message for West Ham vs. Arsenal","description":"","published":"2026-05-09T22:07:27Z","imageUrl":null,"leagueLogo":"https://a.espncdn.com/i/espn/misc_logos/500/espn.png","articleUrl":"https://www.espn.com/video/clip/_/id/48724796/come-irons-guardiola-sends-message-west-ham-vs-arsenal","byline":"","section":"ESPN"}]}