{"fetchedAt":"2026-05-13T03:02:25.418Z","items":[{"id":"2202756","headline":"Victor Wembanyama's 27 points, 17 rebounds power Spurs in Game 5","description":"Victor Wembanyama records 27 points and a playoff career-high 17 rebounds in a Game 5 victory over the Timberwolves.","published":"2026-05-13T02:48:50Z","imageUrl":"https://cdn.nba.com/manage/2026/05/GettyImages-2275901749-Cropped-scaled.jpg","articleUrl":"https://www.nba.com/watch/video/victor-wembanyamas-27-points-17-rebounds-power-spurs-in-game-5","byline":"","section":"NBA Top Videos"},{"id":"2202750","headline":"San Antonio Spurs vs. Minnesota Timberwolves - 4th Quarter Highlights","description":"Watch the 4th Quarter Highlights from San Antonio Spurs vs. Minnesota Timberwolves, 05/12/2026","published":"2026-05-13T02:47:28Z","imageUrl":"https://cdn.nba.com/manage/2026/05/563c4c2a-bda5-45fa-9677-8c286f26321e_0.jpg","articleUrl":"https://www.nba.com/watch/video/san-antonio-spurs-vs-minnesota-timberwolves-4th-quarter-highlights-4","byline":"","section":"NBA Top Videos"},{"id":"2202749","headline":"San Antonio Spurs vs. Minnesota Timberwolves - 2nd Half Highlights","description":"Watch the 2nd Half Highlights from San Antonio Spurs vs. Minnesota Timberwolves, 05/12/2026","published":"2026-05-13T02:47:28Z","imageUrl":"https://cdn.nba.com/manage/2026/05/2f00528f-a836-41f4-875a-db96c4ad2516_0-2.jpg","articleUrl":"https://www.nba.com/watch/video/san-antonio-spurs-vs-minnesota-timberwolves-2nd-half-highlights-4","byline":"","section":"NBA Top Videos"},{"id":"2202737","headline":"Julius Randle ascends for the slam!","description":"Julius Randle ascends for the slam!","published":"2026-05-13T02:38:06Z","imageUrl":"https://cdn.nba.com/manage/2026/05/44489d56-85ff-40e8-9c7d-04bcb0516d00_0.jpg","articleUrl":"https://www.nba.com/watch/video/julius-randle-ascends-for-the-slam-13","byline":"","section":"NBA Top Videos"},{"id":"2202735","headline":"Dunk by Dylan Harper","description":"Dunk by Dylan Harper","published":"2026-05-13T02:37:28Z","imageUrl":"https://cdn.nba.com/manage/2026/05/2ecd980f-9877-49aa-8875-885c12891f1e_0.jpg","articleUrl":"https://www.nba.com/watch/video/dunk-by-dylan-harper-8","byline":"","section":"NBA Top Videos"},{"id":"2202725","headline":"Stephon Castle with the dunk","description":"Stephon Castle with the dunk","published":"2026-05-13T02:23:57Z","imageUrl":"https://cdn.nba.com/manage/2026/05/d3dfd906-2514-48cf-ae9f-47517347829c_0.jpg","articleUrl":"https://www.nba.com/watch/video/stephon-castle-with-the-dunk-17","byline":"","section":"NBA Top Videos"},{"id":"2202722","headline":"Julius Randle with the dunk","description":"Julius Randle with the dunk","published":"2026-05-13T02:23:08Z","imageUrl":"https://cdn.nba.com/manage/2026/05/27cd25bb-bdd5-409d-8735-43a3f91b58a8_0.jpg","articleUrl":"https://www.nba.com/watch/video/julius-randle-with-the-dunk-14","byline":"","section":"NBA Top Videos"},{"id":"2202715","headline":"San Antonio Spurs vs. Minnesota Timberwolves - 3rd Quarter Highlights","description":"Watch the 3rd Quarter Highlights from San Antonio Spurs vs. Minnesota Timberwolves, 05/12/2026","published":"2026-05-13T02:11:16Z","imageUrl":"https://cdn.nba.com/manage/2026/05/2f00528f-a836-41f4-875a-db96c4ad2516_0-1.jpg","articleUrl":"https://www.nba.com/watch/video/san-antonio-spurs-vs-minnesota-timberwolves-3rd-quarter-highlights-4","byline":"","section":"NBA Top Videos"},{"id":"2202709","headline":"Block by Keldon Johnson","description":"Block by Keldon Johnson","published":"2026-05-13T01:54:48Z","imageUrl":"https://cdn.nba.com/manage/2026/05/2f00528f-a836-41f4-875a-db96c4ad2516_0.jpg","articleUrl":"https://www.nba.com/watch/video/block-by-keldon-johnson","byline":"","section":"NBA Top Videos"},{"id":"2202705","headline":"Stephon Castle ascends for the slam!","description":"Stephon Castle ascends for the slam!","published":"2026-05-13T01:51:19Z","imageUrl":"https://cdn.nba.com/manage/2026/05/567dc87c-741a-4368-85ce-c37add282afe_0.jpg","articleUrl":"https://www.nba.com/watch/video/stephon-castle-ascends-for-the-slam-16","byline":"","section":"NBA Top Videos"}]}