{"fetchedAt":"2026-05-03T22:44:53.881Z","items":[{"id":"2190746","headline":"Anthony Black with the dunk","description":"Anthony Black with the dunk","published":"2026-05-03T21:50:04Z","imageUrl":"https://cdn.nba.com/manage/2026/05/2ea1c1ac-1490-40ab-9150-fa7d01583838_0.jpg","articleUrl":"https://www.nba.com/watch/video/anthony-black-with-the-dunk-14","byline":"","section":"NBA Top Videos"},{"id":"2190744","headline":"3-pointer by Tobias Harris","description":"3-pointer by Tobias Harris","published":"2026-05-03T21:48:10Z","imageUrl":"https://cdn.nba.com/manage/2026/05/74a08e82-c4ec-4495-b1b7-77832c1f42db_0.jpg","articleUrl":"https://www.nba.com/watch/video/3-pointer-by-tobias-harris-4","byline":"","section":"NBA Top Videos"},{"id":"2190738","headline":"Detroit Pistons vs. Orlando Magic - 3rd Quarter Highlights","description":"Watch the 3rd Quarter Highlights from Detroit Pistons vs. Orlando Magic, 05/03/2026","published":"2026-05-03T21:36:04Z","imageUrl":"https://cdn.nba.com/manage/2026/05/8df06dc4-bfa9-4f72-b1a2-ca8ddbba63ab_0-1.jpg","articleUrl":"https://www.nba.com/watch/video/detroit-pistons-vs-orlando-magic-3rd-quarter-highlights-6","byline":"","section":"NBA Top Videos"},{"id":"2190734","headline":"Daniss Jenkins with the 3-pointer","description":"Daniss Jenkins with the 3-pointer","published":"2026-05-03T21:34:27Z","imageUrl":"https://cdn.nba.com/manage/2026/05/b31dfc0b-aa1d-4512-b55c-300749c08f9c_0.jpg","articleUrl":"https://www.nba.com/watch/video/daniss-jenkins-with-the-3-pointer","byline":"","section":"NBA Top Videos"},{"id":"2190726","headline":"Paolo Banchero denies the attempt","description":"Paolo Banchero denies the attempt","published":"2026-05-03T21:20:32Z","imageUrl":"https://cdn.nba.com/manage/2026/05/8df06dc4-bfa9-4f72-b1a2-ca8ddbba63ab_0.jpg","articleUrl":"https://www.nba.com/watch/video/paolo-banchero-denies-the-attempt-2","byline":"","section":"NBA Top Videos"},{"id":"2190721","headline":"Cade Cunningham with the slam","description":"Cade Cunningham with the slam","published":"2026-05-03T21:11:26Z","imageUrl":"https://cdn.nba.com/manage/2026/05/99f511bb-a710-4ea0-9b56-fc8581f8b6f6_0.jpg","articleUrl":"https://www.nba.com/watch/video/cade-cunningham-with-the-slam-11","byline":"","section":"NBA Top Videos"},{"id":"2190716","headline":"Duncan Robinson rises up for the dunk","description":"Duncan Robinson rises up for the dunk","published":"2026-05-03T21:09:19Z","imageUrl":"https://cdn.nba.com/manage/2026/05/e3d98825-fdc3-41ae-a6aa-bf4abd4e2570_0.jpg","articleUrl":"https://www.nba.com/watch/video/duncan-robinson-rises-up-for-the-dunk","byline":"","section":"NBA Top Videos"},{"id":"2190714","headline":"Jalen Duren ascends for the slam!","description":"Jalen Duren ascends for the slam!","published":"2026-05-03T21:04:16Z","imageUrl":"https://cdn.nba.com/manage/2026/05/5bbb7d7e-9070-4527-ab5f-95de62ea771a_0-1.jpg","articleUrl":"https://www.nba.com/watch/video/jalen-duren-ascends-for-the-slam-35","byline":"","section":"NBA Top Videos"},{"id":"2190712","headline":"FUS de Rabat vs. Al Ahly","description":"FUS and ASC face off in Rabat, Morocco for the 2026 BAL season.","published":"2026-05-03T21:00:47Z","imageUrl":"https://cdn.nba.com/manage/2026/05/0e29194b-9237-4d33-bc39-5a7b7621be55_0.jpg","articleUrl":"https://www.nba.com/watch/video/fusderabat-vs-alahly-050326","byline":"","section":"NBA Top Videos"},{"id":"2190701","headline":"Tobias Harris drops 17 points in 2nd quarter","description":"Tobias Harris drops 17 points in 2nd quarter","published":"2026-05-03T20:54:54Z","imageUrl":"https://cdn.nba.com/manage/2026/05/Tobias_Harris_1920x1080.jpg","articleUrl":"https://www.nba.com/watch/video/tobias-harris-drops-17-points-in-2nd-quarter","byline":"","section":"NBA Top Videos"}]}