{"fetchedAt":"2026-05-10T22:14:24.604Z","items":[{"id":"2199887","headline":"Dalen Terry ascends for the slam!","description":"Dalen Terry ascends for the slam!","published":"2026-05-10T22:02:31Z","imageUrl":"https://cdn.nba.com/manage/2026/05/b7f09a83-cbbb-45b8-b5f4-a6c3aa1f6c21_0.jpg","articleUrl":"https://www.nba.com/watch/video/dalen-terry-ascends-for-the-slam","byline":"","section":"NBA Top Videos"},{"id":"2199883","headline":"Ariel Hukporti rises up for the dunk","description":"Ariel Hukporti rises up for the dunk","published":"2026-05-10T21:55:18Z","imageUrl":"https://cdn.nba.com/manage/2026/05/0a03623a-af59-4ca7-9f05-65a09727983f_0.jpg","articleUrl":"https://www.nba.com/watch/video/ariel-hukporti-rises-up-for-the-dunk-3","byline":"","section":"NBA Top Videos"},{"id":"2199882","headline":"Dominick Barlow throws it down","description":"Dominick Barlow throws it down","published":"2026-05-10T21:55:17Z","imageUrl":"https://cdn.nba.com/manage/2026/05/fde1a389-7e67-4f27-b478-5192204227dc_0.jpg","articleUrl":"https://www.nba.com/watch/video/dominick-barlow-throws-it-down-14","byline":"","section":"NBA Top Videos"},{"id":"2199870","headline":"Philadelphia 76ers vs. New York Knicks - 3rd Quarter Highlights","description":"Watch the 3rd Quarter Highlights from Philadelphia 76ers vs. New York Knicks, 05/10/2026","published":"2026-05-10T21:41:52Z","imageUrl":"https://cdn.nba.com/manage/2026/05/5e90bb36-106f-4a17-a9ce-9758dcd00a53_0.jpg","articleUrl":"https://www.nba.com/watch/video/philadelphia-76ers-vs-new-york-knicks-3rd-quarter-highlights-4","byline":"","section":"NBA Top Videos"},{"id":"2199861","headline":"Landry Shamet dials from long distance","description":"Landry Shamet dials from long distance","published":"2026-05-10T21:36:22Z","imageUrl":"https://cdn.nba.com/manage/2026/05/1bac3030-e3ed-4377-8fec-503c76eeeac3_0.jpg","articleUrl":"https://www.nba.com/watch/video/landry-shamet-dials-from-long-distance","byline":"","section":"NBA Top Videos"},{"id":"2199858","headline":"Miles McBride gets the And-1","description":"Miles McBride gets the And-1","published":"2026-05-10T21:35:26Z","imageUrl":"https://cdn.nba.com/manage/2026/05/f1b1f252-b207-4175-8fef-f484947bd938_0.jpg","articleUrl":"https://www.nba.com/watch/video/miles-mcbride-gets-the-and-1","byline":"","section":"NBA Top Videos"},{"id":"2199845","headline":"Knicks hit 18 3s in 1st half of Game 4","description":"Knicks hit 18 3s in 1st half of Game 4","published":"2026-05-10T21:17:26Z","imageUrl":"https://cdn.nba.com/manage/2026/05/a8325b5c-1358-4197-a990-6d56485504b8_0.jpg","articleUrl":"https://www.nba.com/watch/video/knicks-hit-18-3s-in-1st-half-of-game-4","byline":"","section":"NBA Top Videos"},{"id":"2199843","headline":"Jalen Brunson with the 3-pointer","description":"Jalen Brunson with the 3-pointer","published":"2026-05-10T21:16:34Z","imageUrl":"https://cdn.nba.com/manage/2026/05/00fbbfc7-ade7-46f8-b362-1ea66d8f5a4c_0.jpg","articleUrl":"https://www.nba.com/watch/video/jalen-brunson-with-the-3-pointer-10","byline":"","section":"NBA Top Videos"},{"id":"2199841","headline":"Mitchell Robinson rises to finish the alley-oop","description":"Mitchell Robinson rises to finish the alley-oop","published":"2026-05-10T21:16:16Z","imageUrl":"https://cdn.nba.com/manage/2026/05/3243ad10-e82e-4485-abb8-b780a464f624_0.jpg","articleUrl":"https://www.nba.com/watch/video/mitchell-robinson-rises-to-finish-the-alley-oop-10","byline":"","section":"NBA Top Videos"},{"id":"2199839","headline":"Paul George drills the triple","description":"Paul George drills the triple","published":"2026-05-10T21:14:22Z","imageUrl":"https://cdn.nba.com/manage/2026/05/dc624dc0-d178-4b87-8602-080d8e4c9d38_0.jpg","articleUrl":"https://www.nba.com/watch/video/paul-george-drills-the-triple-5","byline":"","section":"NBA Top Videos"}]}