{"fetchedAt":"2026-04-25T02:16:36.243Z","items":[{"id":"2177319","headline":"Highlights From Tyrese Maxey 31-Point Game","description":"Highlights From Tyrese Maxey 31-Point Game","published":"2026-04-25T02:02:29Z","imageUrl":"https://cdn.nba.com/manage/2026/04/8f9328ae-a3af-49ec-bc2d-de671cd59325_0.jpg","articleUrl":"https://www.nba.com/watch/video/highlights-from-tyrese-maxey-31-point-game-3","byline":"","section":"NBA Top Videos"},{"id":"2177314","headline":"Highlights From Jayson Tatum 25-Point Game","description":"Highlights From Jayson Tatum 25-Point Game","published":"2026-04-25T02:02:19Z","imageUrl":"https://cdn.nba.com/manage/2026/04/a69e9ede-eb79-48a9-85ba-4ab6cfe571b0_0-1.jpg","articleUrl":"https://www.nba.com/watch/video/highlights-from-jayson-tatum-25-point-game-3","byline":"","section":"NBA Top Videos"},{"id":"2177311","headline":"LeBron James connects from deep","description":"LeBron James connects from deep","published":"2026-04-25T02:01:56Z","imageUrl":"https://cdn.nba.com/manage/2026/04/2dcbb882-f17a-4bc1-8d64-74e415f72233_0.jpg","articleUrl":"https://www.nba.com/watch/video/lebron-james-connects-from-deep-2","byline":"","section":"NBA Top Videos"},{"id":"2177316","headline":"Highlights From Jaylen Brown 25-Point Game","description":"Highlights From Jaylen Brown 25-Point Game","published":"2026-04-25T02:01:42Z","imageUrl":"https://cdn.nba.com/manage/2026/04/d20c9cad-1aa2-4b1b-96fb-b080c9a63f49_0.jpg","articleUrl":"https://www.nba.com/watch/video/highlights-from-jaylen-brown-25-point-game-2","byline":"","section":"NBA Top Videos"},{"id":"2177308","headline":"Jayson Tatum, Jaylen Brown combine for 50 points in Game 3","description":"The Celtics duo both score 25 points each as they lead Boston to a Game 3 win on the road.","published":"2026-04-25T02:01:21Z","imageUrl":"https://cdn.nba.com/manage/2026/04/tatum-76ers-gm3-meta-042426-scaled.jpg","articleUrl":"https://www.nba.com/watch/video/jayson-tatum-jaylen-brown-combine-for-50-points-in-game-3","byline":"","section":"NBA Top Videos"},{"id":"2177294","headline":"Philadelphia 76ers vs. Boston Celtics - 2nd Half Highlights","description":"Watch the 2nd Half Highlights from Philadelphia 76ers vs. Boston Celtics, 04/24/2026","published":"2026-04-25T01:53:30Z","imageUrl":"https://cdn.nba.com/manage/2026/04/2fe82232-2fe3-46b7-9512-e7f317466c7e_0-2.jpg","articleUrl":"https://www.nba.com/watch/video/philadelphia-76ers-vs-boston-celtics-2nd-half-highlights","byline":"","section":"NBA Top Videos"},{"id":"2177291","headline":"BOS vs. PHI Highlights","description":"BOS vs. PHI Highlights","published":"2026-04-25T01:53:05Z","imageUrl":"https://cdn.nba.com/manage/2026/04/6fc0a3c7-d8d3-429d-beb1-e60c56bf4f53_0.jpg","articleUrl":"https://www.nba.com/watch/video/bos-vs-phi-highlights-8","byline":"","section":"NBA Top Videos"},{"id":"2177286","headline":"Philadelphia 76ers vs. Boston Celtics - 4th Quarter Highlights","description":"Watch the 4th Quarter Highlights from Philadelphia 76ers vs. Boston Celtics, 04/24/2026","published":"2026-04-25T01:49:20Z","imageUrl":"https://cdn.nba.com/manage/2026/04/2fe82232-2fe3-46b7-9512-e7f317466c7e_0-1.jpg","articleUrl":"https://www.nba.com/watch/video/philadelphia-76ers-vs-boston-celtics-4th-quarter-highlights-3","byline":"","section":"NBA Top Videos"},{"id":"2177280","headline":"Amen Thompson throws it down","description":"Amen Thompson throws it down","published":"2026-04-25T01:47:06Z","imageUrl":"https://cdn.nba.com/manage/2026/04/8e709c86-132c-48f7-a635-78f7d7a7b150_0.jpg","articleUrl":"https://www.nba.com/watch/video/amen-thompson-throws-it-down-34","byline":"","section":"NBA Top Videos"},{"id":"2177275","headline":"Dunk by Amen Thompson","description":"Dunk by Amen Thompson","published":"2026-04-25T01:44:20Z","imageUrl":"https://cdn.nba.com/manage/2026/04/23d9f3a8-22e7-4a86-9159-e0cdeb55ac9e_0.jpg","articleUrl":"https://www.nba.com/watch/video/dunk-by-amen-thompson-40","byline":"","section":"NBA Top Videos"}]}